pif/__init__.py
pif/base.py
pif/benchmark.py
pif/conf.py
pif/defaults.py
pif/discover.py
pif/exceptions.py
pif/helpers.py
pif/tests.py
pif/utils.py
pif/bin/get-public-ip
pif/checkers/__init__.py
pif/checkers/dyndns/__init__.py
pif/checkers/dyndns/pif_ip_checker.py
pif/checkers/httpbin/__init__.py
pif/checkers/httpbin/pif_ip_checker.py
pif/checkers/icanhazip/__init__.py
pif/checkers/icanhazip/pif_ip_checker.py
pif/checkers/ident/__init__.py
pif/checkers/ident/pif_ip_checker.py
pif/checkers/ip42/__init__.py
pif/checkers/ip42/pif_ip_checker.py
pif/checkers/ipecho/__init__.py
pif/checkers/ipecho/pif_ip_checker.py
pif/checkers/ipify/__init__.py
pif/checkers/ipify/pif_ip_checker.py
pif/checkers/myexternalip/__init__.py
pif/checkers/myexternalip/pif_ip_checker.py
pif/checkers/tnx/__init__.py
pif/checkers/tnx/pif_ip_checker.py
pif/checkers/whatismyip/__init__.py
pif/checkers/whatismyip/pif_ip_checker.py
pif/checkers/wtfismyip/__init__.py
pif/checkers/wtfismyip/pif_ip_checker.py
pif/commands/__init__.py
pif/commands/get_public_ip.py
pif-0.8.2.data/scripts/get-public-ip
pif-0.8.2.dist-info/DESCRIPTION.rst
pif-0.8.2.dist-info/METADATA
pif-0.8.2.dist-info/RECORD
pif-0.8.2.dist-info/WHEEL
pif-0.8.2.dist-info/metadata.json
pif-0.8.2.dist-info/top_level.txt
